search_demo/__init__.py
search_demo/demo.py
search_demo/test.py
search_demo-0.1.dist-info/LICENSE
search_demo-0.1.dist-info/METADATA
search_demo-0.1.dist-info/WHEEL
search_demo-0.1.dist-info/top_level.txt
search_demo-0.1.dist-info/RECORD
