Metadata-Version: 2.1
Name: search-demo
Version: 0.1
Summary: Extremely simple curses search result demo
Home-page: https://github.com/snus-kin/search-demo
Author: Thomas Carroll
Author-email: tcarroll@snufk.in
License: UNKNOWN
Platform: UNKNOWN
Classifier: Programming Language :: Python :: 3
Classifier: License :: OSI Approved :: GNU General Public License v3 (GPLv3)
Classifier: Operating System :: OS Independent
Requires-Python: >=3.6
License-File: LICENSE
